coco_core/__init__.py
coco_core/app.py
coco_core-0.0.2.dist-info/METADATA
coco_core-0.0.2.dist-info/WHEEL
coco_core-0.0.2.dist-info/top_level.txt
coco_core-0.0.2.dist-info/RECORD
